MANIFEST.in
setup.py
pybloom_live/__init__.py
pybloom_live/benchmarks.py
pybloom_live/pybloom.py
pybloom_live/test_pybloom.py
pybloom_live/utils.py
pybloom_live.egg-info/PKG-INFO
pybloom_live.egg-info/SOURCES.txt
pybloom_live.egg-info/dependency_links.txt
pybloom_live.egg-info/requires.txt
pybloom_live.egg-info/top_level.txt
pybloom_live.egg-info/zip-safe