Metadata-Version: 1.1
Name: pybloom-live
Version: 2.3.2
Summary: Bloom filter: A Probabilistic data structure
Home-page: https://github.com/joseph-fox/python-bloomfilter
Author: Jay Baird
Author-email: jay.baird@me.com
License: MIT License
Keywords: data structures,bloom filter,bloom,filter,big data,probabilistic,set
Platform: any
Classifier: Intended Audience :: Developers
Classifier: License :: OSI Approved :: MIT License
Classifier: Programming Language :: Python
Classifier: Programming Language :: Python :: 3
Classifier: Operating System :: OS Independent
Classifier: Topic :: Utilities
Classifier: Topic :: Database :: Database Engines/Servers
Classifier: Topic :: Software Development :: Libraries :: Python Modules
